mkcyarray-1.0.1.dist-info/RECORD
mkcyarray-1.0.1.dist-info/LICENSE
mkcyarray-1.0.1.dist-info/WHEEL
mkcyarray-1.0.1.dist-info/top_level.txt
mkcyarray-1.0.1.dist-info/METADATA
mkcyarray/cyarray.pxd
mkcyarray/__init__.py
mkcyarray/cyarray.c
mkcyarray/cyarray.pyx
mkcyarray/cyarray.cpython-39-darwin.so
mkcyarray/generated/size_t_vector.pxd
mkcyarray/generated/interval_t_vector.pyx
mkcyarray/generated/long_vector.pxd
mkcyarray/generated/double_vector.pyx
mkcyarray/generated/mstr_vector.pyx
mkcyarray/generated/mstr_vector.pxd
mkcyarray/generated/double_vector.pxd
mkcyarray/generated/long_vector.pyx
mkcyarray/generated/interval_t_vector.pxd
mkcyarray/generated/size_t_vector.pyx
mkcyarray/include/mstr.pxd
mkcyarray/include/ivl.pyx
mkcyarray/include/ivl.pxd
mkcyarray/include/mstr.pyx
