Metadata-Version: 2.1
Name: mkcyarray
Version: 1.0.1
Requires-Python: >=3.8
License-File: LICENSE
